nicSpeedyModule.cpython-39-darwin.so
NicSpeedyModule-1.1.1.dist-info/LICENSE
NicSpeedyModule-1.1.1.dist-info/METADATA
NicSpeedyModule-1.1.1.dist-info/WHEEL
NicSpeedyModule-1.1.1.dist-info/top_level.txt
NicSpeedyModule-1.1.1.dist-info/RECORD
