Metadata-Version: 2.1
Name: NicSpeedyModule
Version: 1.1.1
Summary: Package for fetching network interface information
Home-page: https://github.com/LukasMazl/NicSpeedyModule
Author: Lukas Mazl
Author-email: lukasmazl586@gmail.com
License: UNKNOWN
Project-URL: Bug Tracker, https://github.com/LukasMazl/NicSpeedyModule/issues
Platform: UNKNOWN
Classifier: Development Status :: 4 - Beta
Classifier: License :: OSI Approved :: MIT License
Classifier: Operating System :: POSIX
Classifier: Operating System :: MacOS :: MacOS X
Classifier: Topic :: System :: Networking
Classifier: Topic :: System :: Operating System
Classifier: Programming Language :: Python :: 3
Classifier: Programming Language :: Python :: 3.5
Classifier: Programming Language :: Python :: 3.6
Classifier: Programming Language :: Python :: 3.7
Classifier: Programming Language :: Python :: 3.8
Classifier: Programming Language :: Python :: 3.9
Requires-Python: >=3.5
License-File: LICENSE
